lac_validator/__init__.py
lac_validator/__main__.py
lac_validator/config.py
lac_validator/datastore.py
lac_validator/fixtures.py
lac_validator/ingress.py
lac_validator/lac_validator.py
lac_validator/report.py
lac_validator/rule_engine/__init__.py
lac_validator/rule_engine/__registry.py
lac_validator/rules/lac2022_23/__init__.py
lac_validator/rules/lac2022_23/rule_1000.py
lac_validator/rules/lac2022_23/rule_1001.py
lac_validator/rules/lac2022_23/rule_1002.py
lac_validator/rules/lac2022_23/rule_1003.py
lac_validator/rules/lac2022_23/rule_1004.py
lac_validator/rules/lac2022_23/rule_1005.py
lac_validator/rules/lac2022_23/rule_1006.py
lac_validator/rules/lac2022_23/rule_1007.py
lac_validator/rules/lac2022_23/rule_1008.py
lac_validator/rules/lac2022_23/rule_1009.py
lac_validator/rules/lac2022_23/rule_101.py
lac_validator/rules/lac2022_23/rule_1010.py
lac_validator/rules/lac2022_23/rule_1011.py
lac_validator/rules/lac2022_23/rule_1012.py
lac_validator/rules/lac2022_23/rule_1014.py
lac_validator/rules/lac2022_23/rule_1015.py
lac_validator/rules/lac2022_23/rule_102.py
lac_validator/rules/lac2022_23/rule_103.py
lac_validator/rules/lac2022_23/rule_104.py
lac_validator/rules/lac2022_23/rule_105.py
lac_validator/rules/lac2022_23/rule_112.py
lac_validator/rules/lac2022_23/rule_113.py
lac_validator/rules/lac2022_23/rule_114.py
lac_validator/rules/lac2022_23/rule_115.py
lac_validator/rules/lac2022_23/rule_116.py
lac_validator/rules/lac2022_23/rule_117.py
lac_validator/rules/lac2022_23/rule_118.py
lac_validator/rules/lac2022_23/rule_119.py
lac_validator/rules/lac2022_23/rule_120.py
lac_validator/rules/lac2022_23/rule_131.py
lac_validator/rules/lac2022_23/rule_132.py
lac_validator/rules/lac2022_23/rule_133.py
lac_validator/rules/lac2022_23/rule_134.py
lac_validator/rules/lac2022_23/rule_141.py
lac_validator/rules/lac2022_23/rule_142.py
lac_validator/rules/lac2022_23/rule_143.py
lac_validator/rules/lac2022_23/rule_144.py
lac_validator/rules/lac2022_23/rule_145.py
lac_validator-2.0.0.dist-info/METADATA
lac_validator-2.0.0.dist-info/WHEEL
lac_validator-2.0.0.dist-info/RECORD
