Metadata-Version: 2.1
Name: lac-validator
Version: 2.0.0
Summary: Shared module for validating the ruleset on the SSDA903 census using DfE rules.
Home-page: https://github.com/data-to-insight/quality-lac-data-beta-validator
License: MIT
Author: Mark Waddoups
Author-email: mark.waddoups@socialfinance.org.uk
Requires-Python: >=3.9,<4.0
Classifier: License :: OSI Approved :: MIT License
Classifier: Programming Language :: Python :: 3
Classifier: Programming Language :: Python :: 3.9
Classifier: Programming Language :: Python :: 3.10
Classifier: Programming Language :: Python :: 3.11
Requires-Dist: click (>=8.1.3,<9.0.0)
Requires-Dist: click-log (>=0.4.0,<0.5.0)
Requires-Dist: numpy (<1.25.0)
Requires-Dist: openpyxl (>=3.0.9,<4.0.0)
Requires-Dist: pandas (<2.0.0)
Requires-Dist: pre-commit (>=3.3.3,<4.0.0)
Requires-Dist: prpc-python (>=0.9.2,<0.10.0)
Requires-Dist: quality-lac-data-ref-authorities (>=2021.4)
Requires-Dist: quality-lac-data-ref-postcodes (>=2021.8.1)
Requires-Dist: rich (>=13.4.1,<14.0.0)
Requires-Dist: xlrd (>=2.0.1,<3.0.0)
Project-URL: Repository, https://github.com/data-to-insight/quality-lac-data-beta-validator
